ngchat_speech/__init__.py
ngchat_speech/audio.py
ngchat_speech/logger.py
ngchat_speech/ngchat_stt_test.py
ngchat_speech/ngchat_tts_test.py
ngchat_speech/speech.py
ngchat_speech/utils.py
ngchat_speech_sdk-0.1.16.dist-info/LICENSE
ngchat_speech_sdk-0.1.16.dist-info/METADATA
ngchat_speech_sdk-0.1.16.dist-info/WHEEL
ngchat_speech_sdk-0.1.16.dist-info/top_level.txt
ngchat_speech_sdk-0.1.16.dist-info/RECORD
